starlink/Ast.cpython-37m-i386-linux-gnu.so
starlink/Grf.py
starlink/__init__.py
starlink/Atl.py
starlink/include/star/pyast.h
starlink_pyast-3.14.4.dist-info/top_level.txt
starlink_pyast-3.14.4.dist-info/RECORD
starlink_pyast-3.14.4.dist-info/METADATA
starlink_pyast-3.14.4.dist-info/WHEEL
