Metadata-Version: 2.1
Name: starlink-pyast
Version: 3.14.4
Summary: A Python wrapper for the Starlink AST library
Home-page: http://www.starlink.ac.uk/ast
Author: David Berry
Author-email: d.berry@eaobservatory.org
License: UNKNOWN
Platform: UNKNOWN
Classifier: Intended Audience :: Developers
Classifier: License :: OSI Approved :: GNU Lesser General Public License v3 (LGPLv3)
Classifier: Programming Language :: Python
Classifier: Programming Language :: C
Classifier: Topic :: Scientific/Engineering :: Astronomy
Requires-Dist: numpy
